setup.py
python_terminal_dk/__init__.py
python_terminal_dk/terminal.py
python_terminal_dk.egg-info/PKG-INFO
python_terminal_dk.egg-info/SOURCES.txt
python_terminal_dk.egg-info/dependency_links.txt
python_terminal_dk.egg-info/not-zip-safe
python_terminal_dk.egg-info/requires.txt
python_terminal_dk.egg-info/top_level.txt