Metadata-Version: 1.0
Name: python-terminal-dk
Version: 0.3.0
Summary: Alpha version of terminal using python os
Home-page: UNKNOWN
Author: UNKNOWN
Author-email: kuz.damir.01@gmail.com
License: UNKNOWN
Platform: UNKNOWN
